{"skeleton":{"hash":"2eZf6feeafjJPBvPxOerv8AA/fc","spine":"3.8.84","x":-86.73,"y":2.42,"width":171,"height":149,"images":"./images/","audio":"E:/Work/Freelancer-Life/NFTTowerDefend/Animation/Charfx/N"},"bones":[{"name":"root"}],"slots":[{"name":"N_00000","bone":"root","attachment":"N_00000"}],"skins":[{"name":"default","attachments":{"N_00000":{"N_00000":{"x":-1.23,"y":76.92,"width":171,"height":149},"N_00002":{"x":-1.23,"y":68.92,"width":171,"height":135},"N_00004":{"x":-0.23,"y":72.42,"width":169,"height":142},"N_00006":{"x":-0.23,"y":75.42,"width":169,"height":148},"N_00008":{"x":-1.73,"y":79.42,"width":172,"height":156},"N_00010":{"x":-1.23,"y":87.92,"width":171,"height":173},"N_00012":{"x":-1.23,"y":90.42,"width":171,"height":178},"N_00014":{"x":-1.23,"y":97.42,"width":171,"height":192},"N_00016":{"x":-1.23,"y":99.42,"width":171,"height":196},"N_00018":{"x":0.27,"y":103.92,"width":168,"height":205},"N_00020":{"x":0.27,"y":74.42,"width":168,"height":146},"N_00022":{"x":-1.23,"y":77.42,"width":171,"height":152},"N_00024":{"x":-1.23,"y":81.92,"width":171,"height":161},"N_00026":{"x":-1.23,"y":85.92,"width":171,"height":169},"N_00028":{"x":-1.23,"y":83.42,"width":171,"height":162},"N_00030":{"x":-1.23,"y":75.42,"width":171,"height":148},"N_00032":{"x":-0.23,"y":70.92,"width":169,"height":139},"N_00034":{"x":-0.73,"y":75.42,"width":170,"height":148},"N_00036":{"x":-1.23,"y":78.42,"width":171,"height":154},"N_00038":{"x":-1.23,"y":83.92,"width":171,"height":165},"N_00040":{"x":-1.23,"y":87.92,"width":171,"height":173},"N_00042":{"x":-1.23,"y":94.42,"width":171,"height":186},"N_00044":{"x":-1.23,"y":99.42,"width":171,"height":196},"N_00046":{"x":0.27,"y":100.92,"width":168,"height":199},"N_00048":{"x":0.27,"y":70.92,"width":168,"height":139},"N_00050":{"x":-1.23,"y":74.42,"width":171,"height":146},"N_00052":{"x":-1.23,"y":80.42,"width":171,"height":158},"N_00054":{"x":-1.23,"y":85.92,"width":171,"height":169},"N_00056":{"x":-1.23,"y":80.92,"width":171,"height":157},"N_00058":{"x":-1.23,"y":76.42,"width":171,"height":150}}}}],"animations":{"animation":{"slots":{"N_00000":{"attachment":[{"name":"N_00000"},{"time":0.0333,"name":"N_00002"},{"time":0.0667,"name":"N_00004"},{"time":0.1,"name":"N_00006"},{"time":0.1333,"name":"N_00008"},{"time":0.1667,"name":"N_00010"},{"time":0.2,"name":"N_00012"},{"time":0.2333,"name":"N_00014"},{"time":0.2667,"name":"N_00016"},{"time":0.3,"name":"N_00018"},{"time":0.3333,"name":"N_00020"},{"time":0.3667,"name":"N_00022"},{"time":0.4,"name":"N_00024"},{"time":0.4333,"name":"N_00026"},{"time":0.4667,"name":"N_00028"},{"time":0.5,"name":"N_00030"},{"time":0.5333,"name":"N_00032"},{"time":0.5667,"name":"N_00034"},{"time":0.6,"name":"N_00036"},{"time":0.6333,"name":"N_00038"},{"time":0.6667,"name":"N_00040"},{"time":0.7,"name":"N_00042"},{"time":0.7333,"name":"N_00044"},{"time":0.7667,"name":"N_00046"},{"time":0.8,"name":"N_00048"},{"time":0.8333,"name":"N_00050"},{"time":0.8667,"name":"N_00052"},{"time":0.9,"name":"N_00054"},{"time":0.9333,"name":"N_00056"},{"time":0.9667,"name":"N_00058"}]}}}}}